MANIFEST.in
README.rst
setup.cfg
setup.py
bin/check_cluster
monitoring_plugins_crm/__init__.py
monitoring_plugins_crm/crm_check.py
monitoring_plugins_crm.egg-info/PKG-INFO
monitoring_plugins_crm.egg-info/SOURCES.txt
monitoring_plugins_crm.egg-info/dependency_links.txt
monitoring_plugins_crm.egg-info/requires.txt
monitoring_plugins_crm.egg-info/top_level.txt