Metadata-Version: 1.1
Name: monitoring-plugins-crm
Version: 1.0.1
Summary: This script checks the state of resources and nodes.
Home-page: https://github.com/mgrzybek/monitoring-plugins-crm
Author: Mathieu Grzybek
Author-email: mathieu@grzybek.fr
License: GPLv3
Download-URL: https://github.com/mgrzybek/monitoring-plugins-crm/archive/1.0.1.tar.gz
Keywords: monitoring check crm cluster
Platform: UNKNOWN
Classifier: Development Status :: 5 - Production/Stable
Classifier: Topic :: Utilities
Classifier: Environment :: Console
Classifier: License :: OSI Approved :: GNU General Public License v3 or later (GPLv3+)
